{
    "metadata": {
        "dataset name": "Vader dataset",
        "names": {
            "context": "context",
            "label": "label",
            "chatbot": "Vader"
        },
        "semantic similarity": {
            "ordering": [
                "context-label",
                "context-chatbot",
                "chatbot-label",
                "ccl"
            ]
        },
        "perplexity": {
            "ordering": "chatbot"
        },
        "bleu": {
            "ordering": [
                "context-label",
                "context-chatbot",
                "chatbot-label",
                "ccl"
            ]
        },
        "rouge l": {
            "ordering": [
                "context-label",
                "context-chatbot",
                "chatbot-label",
                "ccl"
            ]
        },
        "distinct": {
            "ordering": [
                "context",
                "label",
                "chatbot"
            ]
        },
        "emotion": {
            "ordering": [
                "context-label",
                "context-chatbot",
                "chatbot-label",
                "chatbot-label correlation"
            ]
        },
        "semantic answer similarity": {
            "ordering": [
                "context-label",
                "context-chatbot",
                "chatbot-label",
                "ccl"
            ]
        },
        "semantic classifier": {
            "ordering": [
                "label",
                "chatbot"
            ]
        },
        "human": {
            "ordering": {
                "coherence": "chatbot",
                "consistency": "chatbot",
                "style": "chatbot"
            }
        }
    },
    "semantic similarity": [
        {
            "score": 0.2628566026687622,
            "std": 0.12330655008554459
        },
        {
            "score": 0.5519678592681885,
            "std": 0.2759278416633606
        },
        {
            "score": 0.2198188602924347,
            "std": 0.15027783811092377
        },
        0.27684156841695584
    ],
    "perplexity": 20.615766981008772,
    "bleu": [
        {
            "score": 0.0
        },
        {
            "score": 0.0752434444398826
        },
        {
            "score": 0.0
        },
        0.4275873435257062
    ],
    "rouge l": [
        {
            "score": 0.07925918737060042,
            "std": 0.07479345524211507
        },
        {
            "score": 0.2783069336058467,
            "std": 0.32252310998200084
        },
        {
            "score": 0.05853002070393374,
            "std": 0.0998893999786502
        },
        0.3224751380672207
    ],
    "distinct": [
        {
            "score": 0.114955529740867,
            "std": 0.04780861208267611
        },
        {
            "score": 0.13947061601006405,
            "std": 0.02676100873863562
        },
        {
            "score": 0.08527553732835744,
            "std": 0.06116365236874314
        }
    ],
    "emotion": [
        {
            "score": [
                0.03771194361979724,
                0.3086916868633125,
                0.0028261127226869576,
                0.46144579228712246,
                0.17504403311977512,
                0.01428043059331685
            ],
            "std": [
                0.08578421763279184,
                0.36904829280560575,
                0.0027072039533586954,
                0.3735566079126503,
                0.20110207065098584,
                0.044106013655653725
            ],
            "label": [
                "sadness",
                "joy",
                "love",
                "anger",
                "fear",
                "surprise"
            ]
        },
        {
            "score": [
                0.09321644622832537,
                0.4917986299897166,
                0.005095473637993564,
                0.32870645810180577,
                0.07919873658102006,
                0.0019842915035042097
            ],
            "std": [
                0.21205984751483212,
                0.4378304869670238,
                0.0070275803922158885,
                0.3781002741798295,
                0.1928358104243509,
                0.0024241419183065696
            ],
            "label": [
                "sadness",
                "joy",
                "love",
                "anger",
                "fear",
                "surprise"
            ]
        },
        {
            "score": [
                0.11372547360952012,
                0.3822097205265891,
                0.03265330982321757,
                0.358829681732459,
                0.10793059322895715,
                0.004651219400329865
            ],
            "std": [
                0.2158833609059244,
                0.3765417575013274,
                0.09553062465635066,
                0.36344891732747475,
                0.13852242597426473,
                0.003624156518952487
            ],
            "label": [
                "sadness",
                "joy",
                "love",
                "anger",
                "fear",
                "surprise"
            ]
        },
        0.9735187569110957
    ],
    "semantic answer similarity": [
        {
            "score": 0.06030791625380516,
            "std": 0.08577671647071838
        },
        {
            "score": 0.43145668506622314,
            "std": 0.3515917956829071
        },
        {
            "score": 0.0975886881351471,
            "std": 0.15125875174999237
        },
        0.20248871150903835
    ],
    "semantic classifier": [
        {
            "score": 0.9999648332595825,
            "std": 1.0704990017984528e-05
        },
        {
            "score": 0.4008733034133911,
            "std": 0.4590854346752167
        }
    ],
    "human": {
        "coherence": {
            "score": 0.8,
            "std": 0.0
        },
        "style": {
            "score": 0.2,
            "std": 0.0
        },
        "consistency": {
            "score": 0.2,
            "std": 0.0
        }
    }
}