{
    "greedy_vs_nbeams": {
        "metadata": {
            "ordering": [
                "context-chatbota",
                "context-chatbotb",
                "chatbotb-chatbota",
                "ccl"
            ]
        },
        "semantic answer similarity": [
            {
                "score": 0.14705783128738403,
                "std": 0.19515429437160492
            },
            {
                "score": 0.14705783128738403,
                "std": 0.19515429437160492
            },
            {
                "score": 0.9659613966941833,
                "std": 0.006425890605896711
            },
            0.9665407099516887
        ],
        "bleu": [
            {
                "score": 0.00928096682597953,
                "std": 0.07559592433450453
            },
            {
                "score": 0.00928096682597953,
                "std": 0.07559592433450453
            },
            {
                "score": 0.7625,
                "std": 0.4255511132637301
            },
            0.790703125
        ],
        "rouge l": [
            {
                "score": 0.13229143381999084,
                "std": 0.18661325156423086
            },
            {
                "score": 0.13229143381999084,
                "std": 0.18661325156423086
            },
            {
                "score": 1.0,
                "std": 0.0
            },
            1.0
        ],
        "distinct": [
            {
                "score": 0.12846649729234516,
                "std": 0.055517870859855746
            },
            {
                "score": 0.12761602953306864,
                "std": 0.054898670739709964
            },
            {
                "score": 0.12761602953306864,
                "std": 0.054898670739709964
            },
            0.5072928193853208
        ],
        "emotion": [
            {
                "score": [
                    0.08216332453260596,
                    0.4117479200960588,
                    0.02091454547213895,
                    0.3934890758647574,
                    0.0749480934920939,
                    0.01673704493311258
                ],
                "std": [
                    0.22827820909580038,
                    0.40903970078813684,
                    0.1132092037536279,
                    0.3856237545020503,
                    0.17087921779548867,
                    0.1004992683775623
                ],
                "label": [
                    "sadness",
                    "joy",
                    "love",
                    "anger",
                    "fear",
                    "surprise"
                ]
            },
            {
                "score": [
                    0.12428749160414251,
                    0.3166150558290004,
                    0.030766551927990805,
                    0.4516899977882228,
                    0.07403483558003549,
                    0.002606071124743418
                ],
                "std": [
                    0.2836691205160209,
                    0.3962229885554758,
                    0.11519870084715968,
                    0.41238530277152957,
                    0.18819032583228174,
                    0.008921676358985171
                ],
                "label": [
                    "sadness",
                    "joy",
                    "love",
                    "anger",
                    "fear",
                    "surprise"
                ]
            },
            {
                "score": [
                    0.12428749160414251,
                    0.3166150558290004,
                    0.030766551927990805,
                    0.4516899977882228,
                    0.07403483558003549,
                    0.002606071124743418
                ],
                "std": [
                    0.2836691205160209,
                    0.3962229885554758,
                    0.11519870084715968,
                    0.41238530277152957,
                    0.18819032583228174,
                    0.008921676358985171
                ],
                "label": [
                    "sadness",
                    "joy",
                    "love",
                    "anger",
                    "fear",
                    "surprise"
                ]
            },
            1.0
        ],
        "semantic similarity": [
            {
                "score": 0.3497219681739807,
                "std": 0.18892373144626617
            },
            {
                "score": 0.3497219681739807,
                "std": 0.18892373144626617
            },
            {
                "score": 1.0,
                "std": 1.8242008081870154e-07
            },
            1.0
        ],
        "semantic classifier": [
            {
                "score": 0.4008718729019165,
                "std": 0.458753377199173
            },
            {
                "score": 0.6136115789413452,
                "std": 0.4563232660293579
            }
        ]
    },
    "greedy_vs_sampling": {
        "metadata": {
            "ordering": [
                "context-chatbota",
                "context-chatbotb",
                "chatbotb-chatbota",
                "ccl"
            ]
        },
        "semantic answer similarity": [
            {
                "score": 0.14705783128738403,
                "std": 0.19515429437160492
            },
            {
                "score": 0.07893644273281097,
                "std": 0.12188736349344254
            },
            {
                "score": 0.0756552666425705,
                "std": 0.1453450471162796
            },
            0.4370607329201077
        ],
        "bleu": [
            {
                "score": 0.00928096682597953,
                "std": 0.07559592433450453
            },
            {
                "score": 0.0003839064336958153,
                "std": 0.005935049436196502
            },
            {
                "score": 0.004166666666666667,
                "std": 0.06441510347391792
            },
            0.49115119900508386
        ],
        "rouge l": [
            {
                "score": 0.13229143381999084,
                "std": 0.18661325156423086
            },
            {
                "score": 0.09473491997484067,
                "std": 0.11881894253692356
            },
            {
                "score": 0.10370816022500948,
                "std": 0.13741453062034806
            },
            0.4685264232695785
        ],
        "distinct": [
            {
                "score": 0.12846649729234516,
                "std": 0.055517870859855746
            },
            {
                "score": 0.12761602953306864,
                "std": 0.054898670739709964
            },
            {
                "score": 0.13249167316500335,
                "std": 0.05916096302040596
            },
            0.5079269156174593
        ],
        "emotion": [
            {
                "score": [
                    0.08216332453260596,
                    0.4117479200960588,
                    0.02091454547213895,
                    0.3934890758647574,
                    0.0749480934920939,
                    0.01673704493311258
                ],
                "std": [
                    0.22827820909580038,
                    0.40903970078813684,
                    0.1132092037536279,
                    0.3856237545020503,
                    0.17087921779548867,
                    0.1004992683775623
                ],
                "label": [
                    "sadness",
                    "joy",
                    "love",
                    "anger",
                    "fear",
                    "surprise"
                ]
            },
            {
                "score": [
                    0.12428749160414251,
                    0.3166150558290004,
                    0.030766551927990805,
                    0.4516899977882228,
                    0.07403483558003549,
                    0.002606071124743418
                ],
                "std": [
                    0.2836691205160209,
                    0.3962229885554758,
                    0.11519870084715968,
                    0.41238530277152957,
                    0.18819032583228174,
                    0.008921676358985171
                ],
                "label": [
                    "sadness",
                    "joy",
                    "love",
                    "anger",
                    "fear",
                    "surprise"
                ]
            },
            {
                "score": [
                    0.09276721202883588,
                    0.4362226019830511,
                    0.00967857104066449,
                    0.3891151503432411,
                    0.06339969034218787,
                    0.008816771483179765
                ],
                "std": [
                    0.23086317101708168,
                    0.418269352574028,
                    0.06924124369975124,
                    0.37439766532649826,
                    0.12891846557771905,
                    0.06566176683384857
                ],
                "label": [
                    "sadness",
                    "joy",
                    "love",
                    "anger",
                    "fear",
                    "surprise"
                ]
            },
            0.9461145648664867
        ],
        "semantic similarity": [
            {
                "score": 0.3497219681739807,
                "std": 0.18892373144626617
            },
            {
                "score": 0.3348565995693207,
                "std": 0.16661076247692108
            },
            {
                "score": 0.28659477829933167,
                "std": 0.15908733010292053
            },
            0.5263134044614377
        ],
        "semantic classifier": [
            {
                "score": 0.41456037759780884,
                "std": 0.4644742012023926
            },
            {
                "score": 0.5475760698318481,
                "std": 0.46503567695617676
            }
        ]
    },
    "nbeams_vs_sampling": {
        "metadata": {
            "ordering": [
                "context-chatbota",
                "context-chatbotb",
                "chatbotb-chatbota",
                "ccl"
            ]
        },
        "semantic answer similarity": [
            {
                "score": 0.14705783128738403,
                "std": 0.19515429437160492
            },
            {
                "score": 0.07893644273281097,
                "std": 0.12188736349344254
            },
            {
                "score": 0.0756552666425705,
                "std": 0.1453450471162796
            },
            0.4370607329201077
        ],
        "bleu": [
            {
                "score": 0.00928096682597953,
                "std": 0.07559592433450453
            },
            {
                "score": 0.0003839064336958153,
                "std": 0.005935049436196502
            },
            {
                "score": 0.004166666666666667,
                "std": 0.06441510347391792
            },
            0.49115119900508386
        ],
        "rouge l": [
            {
                "score": 0.13229143381999084,
                "std": 0.18661325156423086
            },
            {
                "score": 0.09473491997484067,
                "std": 0.11881894253692356
            },
            {
                "score": 0.10370816022500948,
                "std": 0.13741453062034806
            },
            0.4685264232695785
        ],
        "distinct": [
            {
                "score": 0.12846649729234516,
                "std": 0.055517870859855746
            },
            {
                "score": 0.12761602953306864,
                "std": 0.054898670739709964
            },
            {
                "score": 0.13249167316500335,
                "std": 0.05916096302040596
            },
            0.5079269156174593
        ],
        "emotion": [
            {
                "score": [
                    0.08216332453260596,
                    0.4117479200960588,
                    0.02091454547213895,
                    0.3934890758647574,
                    0.0749480934920939,
                    0.01673704493311258
                ],
                "std": [
                    0.22827820909580038,
                    0.40903970078813684,
                    0.1132092037536279,
                    0.3856237545020503,
                    0.17087921779548867,
                    0.1004992683775623
                ],
                "label": [
                    "sadness",
                    "joy",
                    "love",
                    "anger",
                    "fear",
                    "surprise"
                ]
            },
            {
                "score": [
                    0.12428749160414251,
                    0.3166150558290004,
                    0.030766551927990805,
                    0.4516899977882228,
                    0.07403483558003549,
                    0.002606071124743418
                ],
                "std": [
                    0.2836691205160209,
                    0.3962229885554758,
                    0.11519870084715968,
                    0.41238530277152957,
                    0.18819032583228174,
                    0.008921676358985171
                ],
                "label": [
                    "sadness",
                    "joy",
                    "love",
                    "anger",
                    "fear",
                    "surprise"
                ]
            },
            {
                "score": [
                    0.09276721202883588,
                    0.4362226019830511,
                    0.00967857104066449,
                    0.3891151503432411,
                    0.06339969034218787,
                    0.008816771483179765
                ],
                "std": [
                    0.23086317101708168,
                    0.418269352574028,
                    0.06924124369975124,
                    0.37439766532649826,
                    0.12891846557771905,
                    0.06566176683384857
                ],
                "label": [
                    "sadness",
                    "joy",
                    "love",
                    "anger",
                    "fear",
                    "surprise"
                ]
            },
            0.9461145648664867
        ],
        "semantic similarity": [
            {
                "score": 0.3497219681739807,
                "std": 0.18892373144626617
            },
            {
                "score": 0.3348565995693207,
                "std": 0.16661076247692108
            },
            {
                "score": 0.28659477829933167,
                "std": 0.15908733010292053
            },
            0.5263134044614377
        ],
        "semantic classifier": [
            {
                "score": 0.4929830729961395,
                "std": 0.4688926935195923
            },
            {
                "score": 0.5143460035324097,
                "std": 0.47034531831741333
            }
        ]
    }
}